MANIFEST.in
README.md
UNLICENSE
setup.py
django_castor.egg-info/PKG-INFO
django_castor.egg-info/SOURCES.txt
django_castor.egg-info/dependency_links.txt
django_castor.egg-info/top_level.txt
djcastor/__init__.py
djcastor/models.py
djcastor/storage.py
djcastor/utils.py