Metadata-Version: 1.0
Name: django-castor
Version: 0.2.1
Summary: A content-addressable storage backend for Django.
Home-page: https://github.com/zacharyvoase/django-castor
Author: Zachary Voase
Author-email: z@zacharyvoase.com
License: UNKNOWN
Platform: UNKNOWN
